scrollingtext/__init__.py
scrollingtext/main.py
scrollingtext-0.0.3.dist-info/METADATA
scrollingtext-0.0.3.dist-info/WHEEL
scrollingtext-0.0.3.dist-info/top_level.txt
scrollingtext-0.0.3.dist-info/RECORD
