Metadata-Version: 2.1
Name: scrollingtext
Version: 0.0.3
Summary: write text in a typewriter style similar to the print() function
Home-page: UNKNOWN
Author: gdsonicpython
Author-email: <hatenal.official@gmail.com>
License: UNKNOWN
Keywords: python,print,typewriter
Platform: UNKNOWN
Classifier: Development Status :: 2 - Pre-Alpha
Classifier: Intended Audience :: Developers
Classifier: Programming Language :: Python :: 3
Classifier: Operating System :: Unix
Classifier: Operating System :: MacOS :: MacOS X
Classifier: Operating System :: Microsoft :: Windows
Requires-Dist: time
Requires-Dist: sys
